[{"client_msg_id":"0be69c2e-0f57-410c-8372-45712003ccf0","type":"message","user":"U03C4RC8X","text":"これもおいしい、気に入った・・・!","ts":"1612584167.105300","team":"T03C4RC8V","reactions":[{"name":"goodpoem","count":1,"users":["UD1FQV38V"]}],"replace_original":false,"delete_original":false,"blocks":[{"type":"rich_text","block_id":"eLe"}]},{"client_msg_id":"d43337d6-ba29-4a40-befc-21077de00a0d","type":"message","user":"U03C4RC8X","text":"\u003chttps://averbodemoment.be/nl/producten/\u003e Averbodeというベルギーのビールのんでます。おいしい","ts":"1612583892.104900","attachments":[{"fallback":"Abdij van Averbode: Brood, Peperkoek, Kaas en Bier - Abdij van Averbode","id":1,"title":"Brood, Peperkoek, Kaas en Bier - Abdij van Averbode","title_link":"https://averbodemoment.be/nl/producten/","text":"Eeuwenoude producten van de abdijgemeenschap op een nieuwe en eigentijdse wijze: brood, peperkoek, kaas en bier van de Abdij van Averbode.","thumb_url":"https://averbodemoment.be/wp-content/uploads/2016/03/producten.jpg","fields":[{"title":"Geschreven door","value":"Het Moment","short":true},{"title":"Geschatte leestijd","value":"14 minuten","short":true}],"blocks":null,"service_name":"Abdij van Averbode","thumb_width":1252,"thumb_height":522,"from_url":"https://averbodemoment.be/nl/producten/","original_url":"https://averbodemoment.be/nl/producten/"}],"team":"T03C4RC8V","replace_original":false,"delete_original":false,"blocks":[{"type":"rich_text","block_id":"nyQ5"}]}]
