[{"type":"message","user":"UJB5VJC2W","text":"<@UJB5VJC2W> has joined the channel","ts":"1557808840.065200","subtype":"channel_join","inviter":"U03C4RC8X","replace_original":false,"delete_original":false,"blocks":null},{"type":"message","user":"UD15AMMFC","text":"<@UD15AMMFC> has joined the channel","ts":"1557808842.065400","subtype":"channel_join","inviter":"U03C4RC8X","replace_original":false,"delete_original":false,"blocks":null},{"client_msg_id":"1347f3f3-7103-46cf-a6ef-67326ee1721f","type":"message","user":"UD15AMMFC","text":":interrobang:","ts":"1557808869.065700","team":"T03C4RC8V","replace_original":false,"delete_original":false,"blocks":null,"source_team":"T03C4RC8V","user_team":"T03C4RC8V"},{"client_msg_id":"6ad932c1-4095-4216-8674-3503a867fde6","type":"message","user":"U03C4RC8X","text":"いよいよ明日 at oak meguro","ts":"1557808881.066000","team":"T03C4RC8V","replace_original":false,"delete_original":false,"blocks":null,"source_team":"T03C4RC8V","user_team":"T03C4RC8V"},{"client_msg_id":"e86a2044-94d8-4542-adb4-365f5c50fa13","type":"message","user":"UD15AMMFC","text":"む、この Slack でユーザ名とかちゃんと設定してなくて誰だこのおたこってなった。","ts":"1557808915.066700","team":"T03C4RC8V","reactions":[{"name":"goodpoem","count":2,"users":["U03C4RC8X","UDDCM376D"]}],"replace_original":false,"delete_original":false,"blocks":null,"source_team":"T03C4RC8V","user_team":"T03C4RC8V"},{"client_msg_id":"57852B8F-382C-4464-87B3-2CC94B19892C","type":"message","user":"UDDCM376D","text":"いよいよ明日","ts":"1557810111.067400","team":"T03C4RC8V","replace_original":false,"delete_original":false,"blocks":null,"source_team":"T03C4RC8V","user_team":"T03C4RC8V"},{"client_msg_id":"DA078200-6177-4AFF-B3B0-1A04854101D6","type":"message","user":"UDDCM376D","text":"楽しみ","ts":"1557810126.068000","team":"T03C4RC8V","replace_original":false,"delete_original":false,"blocks":null,"source_team":"T03C4RC8V","user_team":"T03C4RC8V"},{"client_msg_id":"618f2768-bd70-458a-9956-4bf78c1bd186","type":"message","user":"U03C71D7H","text":"イベントの流れとか、特に終わった後どうするとかってあります?","ts":"1557825254.068300","team":"T03C4RC8V","replace_original":false,"delete_original":false,"blocks":null,"source_team":"T03C4RC8V","user_team":"T03C4RC8V"},{"client_msg_id":"5524E418-C0EC-4038-BD93-22159A35CE03","type":"message","user":"UDDCM376D","text":"あ、発表の順番決めます","ts":"1557837358.068700","team":"T03C4RC8V","replace_original":false,"delete_original":false,"blocks":null,"source_team":"T03C4RC8V","user_team":"T03C4RC8V"},{"client_msg_id":"96424740-1CBA-410E-91BC-4ECA5B984094","type":"message","user":"UDDCM376D","text":"終わった後は、有志で複数人で居酒屋に行こうと思ってます\n<@U03C4RC8X> さんは強制参加で","ts":"1557837400.069700","team":"T03C4RC8V","replace_original":false,"delete_original":false,"blocks":null,"source_team":"T03C4RC8V","user_team":"T03C4RC8V"},{"client_msg_id":"368001D1-3BE2-4285-B3AE-69FD99C5DAF7","type":"message","user":"U03C4RC8X","text":"禁煙の店に限り、行きます！","ts":"1557842608.070100","team":"T03C4RC8V","replace_original":false,"delete_original":false,"blocks":null,"source_team":"T03C4RC8V","user_team":"T03C4RC8V"},{"client_msg_id":"ddad84a0-e61e-4338-96c1-620502426e68","type":"message","user":"UDDCM376D","text":"了解ですー","ts":"1557843557.070500","team":"T03C4RC8V","replace_original":false,"delete_original":false,"blocks":null,"source_team":"T03C4RC8V","user_team":"T03C4RC8V"},{"client_msg_id":"68d9b1ea-69d4-4183-89c2-c4cb6d698067","type":"message","user":"UDDCM376D","text":"店は、まったく探していないのですが、<@U03C71D7H> さんにお願いできますか？","ts":"1557843576.071000","team":"T03C4RC8V","replace_original":false,"delete_original":false,"blocks":null,"source_team":"T03C4RC8V","user_team":"T03C4RC8V"},{"client_msg_id":"f3ebf186-9c50-46a8-b614-fd8bf294dc0b","type":"message","user":"UDDCM376D","text":"あ、あと明日発表者一名体調不良で参加できなくなったので、\n他に発表する方いますか？\n<@U03C4RC8X> 日本離れる前なので、発表しますか？","ts":"1557843627.072000","team":"T03C4RC8V","replace_original":false,"delete_original":false,"blocks":null,"source_team":"T03C4RC8V","user_team":"T03C4RC8V"},{"client_msg_id":"656209ed-e815-40b7-95db-4772b9b46b3e","type":"message","user":"UDDCM376D","text":"<https://gorillavim.connpass.com/event/130105/>\nとりあえず飛び入りLTにしてみた","ts":"1557844489.072300","attachments":[{"fallback":"connpass: ゴリラ.vim #4 (2019/05/15 19:00〜)","id":1,"title":"ゴリラ.vim #4 (2019/05/15 19:00〜)","title_link":"https://gorillavim.connpass.com/event/130105/","text":"# 概要 第4回目の開催です！ 今回は株式会社アカツキ様が会場を提供してくださります。 また、懇親会はないので事前もしくは参加しながら食事をとって頂ければと思います。 # ゴリラ.vimについて vimmerの集いの会です。 知見の共有と親睦を深めることを目的としています。 月一ペースで都内近辺でVimに関するLTとvimmer懇親会をします。 詳細はこちらの資料をご参照ください。 # 対象者 * Vimに興味ある方 * Vim大好きな方 * Vimってなんぞやって方 全員大歓迎です。 ぜひご応募ください！ # 会場について * 飲...","thumb_url":"https://connpass-tokyo.s3.amazonaws.com/thumbs/bc/2c/bc2c87ca4c11a5135f132d867783f5d8.png","blocks":null,"service_name":"connpass","service_icon":"https://connpass.com/static/img/apple_touch_icon.png","thumb_width":468,"thumb_height":468,"from_url":"https://gorillavim.connpass.com/event/130105/","original_url":"https://gorillavim.connpass.com/event/130105/"}],"team":"T03C4RC8V","replace_original":false,"delete_original":false,"blocks":null,"source_team":"T03C4RC8V","user_team":"T03C4RC8V"},{"client_msg_id":"191a9017-9d14-4c25-acfd-ae9753288045","type":"message","user":"U03C4RC8X","text":"誰もいなかったら急に僕にふってもokです","ts":"1557845679.073000","team":"T03C4RC8V","replace_original":false,"delete_original":false,"blocks":null,"source_team":"T03C4RC8V","user_team":"T03C4RC8V"}]
