[{"client_msg_id":"2b0351e6-ee19-40c9-9da5-d0d438b32591","type":"message","user":"U782D5DF1","text":"<https://twitter.com/miyagaw61/statuses/1033976049850245121>","ts":"1535420507.000100","attachments":[{"fallback":"<https://twitter.com/miyagaw61|@miyagaw61>: さ 流石にそれvimでできますよ\nし 知ってましたか？それvimでできますよ\nす すいませんが、それvimでできますよ\nせ せっかくですが、それvimでできますよ\nそ それvimでできますよ","id":1,"author_name":"\"miyagaw\\x61\"","author_subname":"@miyagaw61","author_link":"https://twitter.com/miyagaw61/status/1033976049850245121","author_icon":"https://pbs.twimg.com/profile_images/735412795919892480/w2cAqdfV_normal.jpg","text":"さ 流石にそれvimでできますよ\nし 知ってましたか？それvimでできますよ\nす すいませんが、それvimでできますよ\nせ せっかくですが、それvimでできますよ\nそ それvimでできますよ","blocks":null,"footer":"Twitter","footer_icon":"https://a.slack-edge.com/80588/img/services/twitter_pixel_snapped_32.png","ts":1535354075,"service_name":"twitter","from_url":"https://twitter.com/miyagaw61/statuses/1033976049850245121","original_url":"https://twitter.com/miyagaw61/statuses/1033976049850245121"}],"team":"T03C4RC8V","replace_original":false,"delete_original":false,"blocks":null,"source_team":"T03C4RC8V","user_team":"T03C4RC8V"},{"client_msg_id":"8d618e0e-6575-4c57-97cf-293989179c70","type":"message","user":"U782D5DF1","text":"強い","ts":"1535420513.000100","team":"T03C4RC8V","replace_original":false,"delete_original":false,"blocks":null,"source_team":"T03C4RC8V","user_team":"T03C4RC8V"},{"client_msg_id":"8c9bab15-aeda-4727-85fe-e976e2a63b2c","type":"message","user":"U03C4RC8X","text":"ば行でもやらなければ","ts":"1535420572.000100","team":"T03C4RC8V","replace_original":false,"delete_original":false,"blocks":null,"source_team":"T03C4RC8V","user_team":"T03C4RC8V"},{"client_msg_id":"514f1ce5-c7f5-44e7-b237-6b99550293e2","type":"message","user":"U03C4RC8X","text":"ふ　フハハハハハ","ts":"1535420581.000100","team":"T03C4RC8V","replace_original":false,"delete_original":false,"blocks":null,"source_team":"T03C4RC8V","user_team":"T03C4RC8V"},{"client_msg_id":"29b9f8d8-edff-41bc-956a-1590c610ea59","type":"message","user":"U03C71D7H","text":"なんで `は` じゃなくて `ふ` で始まるのか","ts":"1535420616.000100","team":"T03C4RC8V","reactions":[{"name":"kzk","count":2,"users":["U03C4RC8X","U8CC7MDCL"]}],"replace_original":false,"delete_original":false,"blocks":null,"source_team":"T03C4RC8V","user_team":"T03C4RC8V"},{"client_msg_id":"5fea681e-d87d-4745-8703-45f3d9049a87","type":"message","user":"U03C4RC8X","text":"<https://twitter.com/shiena/status/1034111873413599232>\n<https://twitter.com/NirAtni/status/1034115064318443520>\n<https://twitter.com/mathbbN/status/1034122321999495168>\n<https://twitter.com/27Cobalter/status/1033992972025573376>","ts":"1535420757.000100","attachments":[{"fallback":"<https://twitter.com/shiena|@shiena>: VimConfのチケットいつからかなーと思ったら明日からだったんで忘れないようにしないと\n\nvim-jp » VimConf 2018のチケット販売を開始します <https://vim-jp.org/blog/2018/08/22/vimconf2018-tickets-available-ja.html> <https://twitter.com/vim_jp|@vim_jp>さんから","id":1,"author_name":"Mitsuhiro Koga","author_subname":"@shiena","author_link":"https://twitter.com/shiena/status/1034111873413599232","author_icon":"https://pbs.twimg.com/profile_images/1115971889/20100808220505_normal.jpg","text":"VimConfのチケットいつからかなーと思ったら明日からだったんで忘れないようにしないと\n\nvim-jp » VimConf 2018のチケット販売を開始します <https://vim-jp.org/blog/2018/08/22/vimconf2018-tickets-available-ja.html> <https://twitter.com/vim_jp|@vim_jp>さんから","blocks":null,"footer":"Twitter","footer_icon":"https://a.slack-edge.com/80588/img/services/twitter_pixel_snapped_32.png","ts":1535386458,"service_name":"twitter","from_url":"https://twitter.com/shiena/status/1034111873413599232","original_url":"https://twitter.com/shiena/status/1034111873413599232"},{"fallback":"<https://twitter.com/NirAtni|@NirAtni>: ア、VimConf2018のチケット発売日なのか","id":2,"author_name":"ソファが欲しい！","author_subname":"@NirAtni","author_link":"https://twitter.com/NirAtni/status/1034115064318443520","author_icon":"https://pbs.twimg.com/profile_images/542709986195816450/PvFerVzq_normal.jpeg","text":"ア、VimConf2018のチケット発売日なのか","blocks":null,"footer":"Twitter","footer_icon":"https://a.slack-edge.com/80588/img/services/twitter_pixel_snapped_32.png","ts":1535387218,"service_name":"twitter","from_url":"https://twitter.com/NirAtni/status/1034115064318443520","original_url":"https://twitter.com/NirAtni/status/1034115064318443520"},{"fallback":"<https://twitter.com/mathbbN|@mathbbN>: vimconfのチケット買おうかな\n明日1時、8000円","id":3,"author_name":"ℕ","author_subname":"@mathbbN","author_link":"https://twitter.com/mathbbN/status/1034122321999495168","author_icon":"https://pbs.twimg.com/profile_images/1018137140230701057/fdXw_pMT_normal.jpg","text":"vimconfのチケット買おうかな\n明日1時、8000円","blocks":null,"footer":"Twitter","footer_icon":"https://a.slack-edge.com/80588/img/services/twitter_pixel_snapped_32.png","ts":1535388949,"service_name":"twitter","from_url":"https://twitter.com/mathbbN/status/1034122321999495168","original_url":"https://twitter.com/mathbbN/status/1034122321999495168"},{"fallback":"<https://twitter.com/27Cobalter|@27Cobalter>: VimConf2018のチケット発売明後日か 休みとっとけばよかった","id":4,"author_name":"コバルト","author_subname":"@27Cobalter","author_link":"https://twitter.com/27Cobalter/status/1033992972025573376","author_icon":"https://pbs.twimg.com/profile_images/708941923554230272/zaLdbVjV_normal.jpg","text":"VimConf2018のチケット発売明後日か 休みとっとけばよかった","blocks":null,"footer":"Twitter","footer_icon":"https://a.slack-edge.com/80588/img/services/twitter_pixel_snapped_32.png","ts":1535358109,"service_name":"twitter","from_url":"https://twitter.com/27Cobalter/status/1033992972025573376","original_url":"https://twitter.com/27Cobalter/status/1033992972025573376"}],"team":"T03C4RC8V","replace_original":false,"delete_original":false,"blocks":null,"source_team":"T03C4RC8V","user_team":"T03C4RC8V"},{"client_msg_id":"bc683566-fdb1-42a3-89f0-6090e3840b4a","type":"message","user":"U7JL1UKKL","text":"<https://employment.en-japan.com/engineerhub/entry/2018/08/28/110000>","ts":"1535424380.000100","attachments":[{"fallback":"エンジニアHub｜若手Webエンジニアのキャリアを考える！: deoplete.nvim開発者、Shougoが考える「Viｍの限界ギリギリ」を攻めるプラグイン開発の裏側 #エンジニアHub - エンジニアHub｜若手Webエンジニアのキャリアを考える！","id":1,"title":"deoplete.nvim開発者、Shougoが考える「Viｍの限界ギリギリ」を攻めるプラグイン開発の裏側 #エンジニアHub - エンジニアHub｜若手Webエンジニアのキャリアを考える！","title_link":"https://employment.en-japan.com/engineerhub/entry/2018/08/28/110000","text":"多くのエンジニアに愛されるテキストエディタ『Vim』のプラグインを作り続けるShougoさん。Vimmerならば一度は使ったことがある、というほどに広く知られたプラグインを作り続ける理由を聞きました。","image_url":"https://cdn-ak.f.st-hatena.com/images/fotolife/b/blog-media/20180820/20180820170418.jpg","blocks":null,"ts":1535421600,"service_name":"エンジニアHub｜若手Webエンジニアのキャリアを考える！","service_icon":"https://cdn.image.st-hatena.com/image/favicon/c01d5013ad03911d2cd2f59862ac3cf994927108/version=1/https%3A%2F%2Fcdn.user.blog.st-hatena.com%2Fcustom_blog_icon%2F125375497%2F1514216060853259","from_url":"https://employment.en-japan.com/engineerhub/entry/2018/08/28/110000","original_url":"https://employment.en-japan.com/engineerhub/entry/2018/08/28/110000"}],"team":"T03C4RC8V","reactions":[{"name":"vim_gantan","count":4,"users":["U0M7GCBPD","UCFEJF487","U7TMPGWJ0","UBDMG6N2J"]},{"name":"vimvim","count":1,"users":["U7CJ2P52B"]}],"replace_original":false,"delete_original":false,"blocks":null,"source_team":"T03C4RC8V","user_team":"T03C4RC8V"},{"client_msg_id":"82f5e371-e7e4-4b0b-aa8e-7f9f9279b985","type":"message","user":"U7JL1UKKL","text":"インタビュー記事が公開されましたのでどうぞ","ts":"1535424392.000100","team":"T03C4RC8V","replace_original":false,"delete_original":false,"blocks":null,"source_team":"T03C4RC8V","user_team":"T03C4RC8V"},{"client_msg_id":"FB45A6EF-A126-4B06-9C77-9C392FCE408E","type":"message","user":"U03C4RC8X","text":"おっ！！！","ts":"1535424406.000100","team":"T03C4RC8V","replace_original":false,"delete_original":false,"blocks":null,"source_team":"T03C4RC8V","user_team":"T03C4RC8V"},{"client_msg_id":"3679762a-4cc8-43e5-90f7-a2cdc267418b","type":"message","user":"U03C71D7H","text":"顔を隠す意味あるんかなw","ts":"1535424971.000100","team":"T03C4RC8V","replace_original":false,"delete_original":false,"blocks":null,"source_team":"T03C4RC8V","user_team":"T03C4RC8V"},{"client_msg_id":"2d2fcab0-b970-4156-b6f8-98bc95f133c4","type":"message","user":"U03C71D7H","text":"(普段割とイベント等で顔出ししてるイメージあるので)","ts":"1535425206.000100","team":"T03C4RC8V","replace_original":false,"delete_original":false,"blocks":null,"source_team":"T03C4RC8V","user_team":"T03C4RC8V"},{"client_msg_id":"f7aeb60f-e6e1-4396-b1de-5d0e44149210","type":"message","user":"U7JL1UKKL","text":"今回はイベントではなくWeb記事なので慎重になった","ts":"1535426008.000100","team":"T03C4RC8V","replace_original":false,"delete_original":false,"blocks":null,"source_team":"T03C4RC8V","user_team":"T03C4RC8V"},{"client_msg_id":"62909b83-e6fd-479c-99f2-1ddcc4b1f036","type":"message","user":"U03C71D7H","text":"なるほど","ts":"1535426857.000100","team":"T03C4RC8V","replace_original":false,"delete_original":false,"blocks":null,"source_team":"T03C4RC8V","user_team":"T03C4RC8V"},{"type":"message","user":"U77E0CBHQ","ts":"1535427049.000100","files":[{"id":"FCGA4JJDQ","created":1535427047,"timestamp":1535427047,"name":"Screen Shot 2018-08-28 at 12.30.26.png","title":"Screen Shot 2018-08-28 at 12.30.26.png","mimetype":"image/png","image_exif_rotation":1,"filetype":"png","pretty_type":"PNG","user":"U77E0CBHQ","mode":"hosted","editable":false,"is_external":false,"external_type":"","size":115572,"url":"","url_download":"","url_private":"https://files.slack.com/files-pri/T03C4RC8V-FCGA4JJDQ/screen_shot_2018-08-28_at_12.30.26.png","url_private_download":"https://files.slack.com/files-pri/T03C4RC8V-FCGA4JJDQ/download/screen_shot_2018-08-28_at_12.30.26.png","original_h":397,"original_w":428,"thumb_64":"https://files.slack.com/files-tmb/T03C4RC8V-FCGA4JJDQ-b8be64ba18/screen_shot_2018-08-28_at_12.30.26_64.png","thumb_80":"https://files.slack.com/files-tmb/T03C4RC8V-FCGA4JJDQ-b8be64ba18/screen_shot_2018-08-28_at_12.30.26_80.png","thumb_160":"https://files.slack.com/files-tmb/T03C4RC8V-FCGA4JJDQ-b8be64ba18/screen_shot_2018-08-28_at_12.30.26_160.png","thumb_360":"https://files.slack.com/files-tmb/T03C4RC8V-FCGA4JJDQ-b8be64ba18/screen_shot_2018-08-28_at_12.30.26_360.png","thumb_360_gif":"","thumb_360_w":360,"thumb_360_h":334,"thumb_480":"","thumb_480_w":0,"thumb_480_h":0,"thumb_720":"","thumb_720_w":0,"thumb_720_h":0,"thumb_960":"","thumb_960_w":0,"thumb_960_h":0,"thumb_1024":"","thumb_1024_w":0,"thumb_1024_h":0,"permalink":"https://vim-jp.slack.com/files/U77E0CBHQ/FCGA4JJDQ/screen_shot_2018-08-28_at_12.30.26.png","permalink_public":"https://slack-files.com/T03C4RC8V-FCGA4JJDQ-22ae63b68f","edit_link":"","preview":"","preview_highlight":"","lines":0,"lines_more":0,"is_public":true,"public_url_shared":false,"channels":null,"groups":null,"ims":null,"initial_comment":{},"comments_count":0,"num_stars":0,"is_starred":false,"shares":{"public":null,"private":null},"display_as_bot":false,"has_rich_preview":false,"username":""}],"upload":true,"replace_original":false,"delete_original":false,"blocks":null},{"client_msg_id":"97428f1a-3174-434e-8ba1-386ac7f422da","type":"message","user":"U77E0CBHQ","text":"なるほどぉ","ts":"1535427059.000100","team":"T03C4RC8V","replace_original":false,"delete_original":false,"blocks":null,"source_team":"T03C4RC8V","user_team":"T03C4RC8V"},{"client_msg_id":"02f6428f-1972-441b-92bb-5116e9c84d97","type":"message","user":"U77E0CBHQ","text":"(もちろん別人です)","ts":"1535427110.000100","team":"T03C4RC8V","replace_original":false,"delete_original":false,"blocks":null,"source_team":"T03C4RC8V","user_team":"T03C4RC8V"},{"client_msg_id":"52e85e56-ba7d-4bcc-b07e-6afee32cbe58","type":"message","user":"U782D5DF1","text":"すごい","ts":"1535427458.000100","team":"T03C4RC8V","replace_original":false,"delete_original":false,"blocks":null,"source_team":"T03C4RC8V","user_team":"T03C4RC8V"},{"client_msg_id":"05010961-c8cc-4bc0-879c-77f3083a3b6d","type":"message","user":"U06ECBRTJ","text":"初めてShougoさんに会ったときは、若いなぁと感じた","ts":"1535427763.000100","team":"T03C4RC8V","replace_original":false,"delete_original":false,"blocks":null,"source_team":"T03C4RC8V","user_team":"T03C4RC8V"},{"client_msg_id":"40ef7cbe-f111-4221-895f-23c0573ec819","type":"message","user":"U8996GYBF","text":"leximaとlspとleximaの組み合わせでneovimがフリーズして死ぬっぽくてとても辛い・・・","ts":"1535431082.000100","team":"T03C4RC8V","replace_original":false,"delete_original":false,"blocks":null,"source_team":"T03C4RC8V","user_team":"T03C4RC8V"},{"client_msg_id":"07ce0293-1e31-4492-9583-07bb9e78a0ae","type":"message","user":"U8996GYBF","text":"lspというかtsserver？かな","ts":"1535431253.000100","team":"T03C4RC8V","replace_original":false,"delete_original":false,"blocks":null,"source_team":"T03C4RC8V","user_team":"T03C4RC8V"},{"client_msg_id":"43b2f523-189d-4930-a87a-564bb7eca471","type":"message","user":"U06ECBRTJ","text":"&gt; leximaとlspとleximaの組み合わせ\n大事なことなので2回言われる lexima","ts":"1535433220.000100","edited":{"user":"U06ECBRTJ","ts":"1535433234.000000"},"team":"T03C4RC8V","replace_original":false,"delete_original":false,"blocks":null,"source_team":"T03C4RC8V","user_team":"T03C4RC8V"},{"client_msg_id":"1a4ae846-4208-4c36-b699-88c887afc192","type":"message","user":"U9S4G0LJW","text":"lexima 読み方 検索","ts":"1535434001.000100","team":"T03C4RC8V","replace_original":false,"delete_original":false,"blocks":null,"source_team":"T03C4RC8V","user_team":"T03C4RC8V"},{"client_msg_id":"c148c26d-f86d-431e-97ce-daf30e11ff90","type":"message","user":"U06ECBRTJ","text":"<http://cache.gyazo.com/4ae122b944ad912283e5d9eac4aae22a.png>","ts":"1535434551.000100","attachments":[{"fallback":"322x73px image","id":1,"image_url":"http://cache.gyazo.com/4ae122b944ad912283e5d9eac4aae22a.png","blocks":null,"from_url":"http://cache.gyazo.com/4ae122b944ad912283e5d9eac4aae22a.png","original_url":"http://cache.gyazo.com/4ae122b944ad912283e5d9eac4aae22a.png"}],"team":"T03C4RC8V","reactions":[{"name":"benri","count":5,"users":["U9S4G0LJW","UBN069G3T","U78A6ESHM","U7JL1UKKL","U8CC7MDCL"]}],"replace_original":false,"delete_original":false,"blocks":null,"source_team":"T03C4RC8V","user_team":"T03C4RC8V"},{"client_msg_id":"182b0225-dc4c-41d2-a162-656b1dc152a0","type":"message","user":"U06ECBRTJ","text":"!lexima","ts":"1535434589.000100","team":"T03C4RC8V","replace_original":false,"delete_original":false,"blocks":null,"source_team":"T03C4RC8V","user_team":"T03C4RC8V"},{"type":"message","user":"USLACKBOT","text":"<http://cache.gyazo.com/4ae122b944ad912283e5d9eac4aae22a.png>","ts":"1535434590.000100","subtype":"slackbot_response","replace_original":false,"delete_original":false,"blocks":null},{"client_msg_id":"5792158b-2239-46ef-92e5-4454a3791a00","type":"message","user":"U8996GYBF","text":"あ、最後leximaじゃないですね","ts":"1535437190.000100","team":"T03C4RC8V","replace_original":false,"delete_original":false,"blocks":null,"source_team":"T03C4RC8V","user_team":"T03C4RC8V"},{"client_msg_id":"d1df665a-f68b-4547-a9b0-8b357b84b449","type":"message","user":"U8996GYBF","text":"leximaとlspとdeopleteでした","ts":"1535437198.000100","team":"T03C4RC8V","replace_original":false,"delete_original":false,"blocks":null,"source_team":"T03C4RC8V","user_team":"T03C4RC8V"},{"client_msg_id":"f3d7b166-2975-4535-b97e-245919f988ba","type":"message","user":"U8996GYBF","text":"エラー報告だけでもした方がいいかなぁ","ts":"1535437211.000100","team":"T03C4RC8V","replace_original":false,"delete_original":false,"blocks":null,"source_team":"T03C4RC8V","user_team":"T03C4RC8V"},{"client_msg_id":"b2c5648f-98cf-43c0-b74f-d6f28b06ce2f","type":"message","user":"U8996GYBF","text":"どこにするべきなのか難しいですが・・・","ts":"1535437221.000100","team":"T03C4RC8V","replace_original":false,"delete_original":false,"blocks":null,"source_team":"T03C4RC8V","user_team":"T03C4RC8V"},{"client_msg_id":"43b27504-f6f1-4091-98d0-275b754a101c","type":"message","user":"U03C71D7H","text":"組み合わせの場合は結構困りますねー。一番いいのは原因を特定することなんですが、それなりに労力と時間を割く必要があるし、ノウハウも必要","ts":"1535437282.000100","team":"T03C4RC8V","replace_original":false,"delete_original":false,"blocks":null,"source_team":"T03C4RC8V","user_team":"T03C4RC8V"},{"client_msg_id":"a0f30957-5d33-445f-805c-a443f7767bdf","type":"message","user":"U7JL1UKKL","text":"vim-lspは単体でも動くはずなので、試してみては？","ts":"1535437320.000100","team":"T03C4RC8V","replace_original":false,"delete_original":false,"blocks":null,"source_team":"T03C4RC8V","user_team":"T03C4RC8V"},{"client_msg_id":"148c9dfa-685c-4ce4-bda4-338ccbc9e1bf","type":"message","user":"U7JL1UKKL","text":"deoplete, leximaが再現に必須なのだろうか確認した方がよいと思います","ts":"1535437365.000100","team":"T03C4RC8V","replace_original":false,"delete_original":false,"blocks":null,"source_team":"T03C4RC8V","user_team":"T03C4RC8V"},{"client_msg_id":"b72057b6-0836-4059-8ff1-b5878c4c89ad","type":"message","user":"U8996GYBF","text":"具体的にはnvim-typescriptかLanguageClient-neovimの補完を使ったときに、tsxファイルのjsxのコンテキストで{}をleximaで展開した瞬間にフリーズ、が再現条件なのですが","ts":"1535437365.000200","team":"T03C4RC8V","replace_original":false,"delete_original":false,"blocks":null,"source_team":"T03C4RC8V","user_team":"T03C4RC8V"},{"client_msg_id":"4e5703b5-156a-477a-9b5e-54fd5b791c1c","type":"message","user":"U03C71D7H","text":"再現度が100%なら原因の特定は簡単な部類","ts":"1535437427.000100","team":"T03C4RC8V","replace_original":false,"delete_original":false,"blocks":null,"source_team":"T03C4RC8V","user_team":"T03C4RC8V"},{"client_msg_id":"8061babc-6af4-4501-bbe9-5b49661917b6","type":"message","user":"U8996GYBF","text":"deopleteとleximaだと思います、補完候補からそのsourceを削除したときに動作したのと、leximaをバッファで無効にしたら問題なかった、というかそういう風にして書いているので","ts":"1535437451.000100","team":"T03C4RC8V","replace_original":false,"delete_original":false,"blocks":null,"source_team":"T03C4RC8V","user_team":"T03C4RC8V"},{"client_msg_id":"e968284c-afec-4539-b064-996b98e98ac3","type":"message","user":"U7JL1UKKL","text":"Language-Client neovimはオムニ補完で候補を出せるはずなので","ts":"1535437454.000100","team":"T03C4RC8V","replace_original":false,"delete_original":false,"blocks":null,"source_team":"T03C4RC8V","user_team":"T03C4RC8V"},{"client_msg_id":"6b383fff-432d-459a-8e21-48657731065b","type":"message","user":"U7JL1UKKL","text":"だとすると、同時使用によるコンフリクトかな","ts":"1535437479.000100","team":"T03C4RC8V","replace_original":false,"delete_original":false,"blocks":null,"source_team":"T03C4RC8V","user_team":"T03C4RC8V"},{"client_msg_id":"bf3dc7df-c8cc-4f26-b7b2-f43c14da6a88","type":"message","user":"U7JL1UKKL","text":"動くタイミングが同じはずなのでありえる","ts":"1535437493.000100","team":"T03C4RC8V","replace_original":false,"delete_original":false,"blocks":null,"source_team":"T03C4RC8V","user_team":"T03C4RC8V"},{"client_msg_id":"02518388-4553-4518-880c-53c5b0d853cd","type":"message","user":"U8996GYBF","text":"LanguageClident-neovimはいいとして、nvim-typescriptの方は型まで表示してくれるから便利なんですよね。ちょっとどうするか考えてます。","ts":"1535437500.000100","team":"T03C4RC8V","replace_original":false,"delete_original":false,"blocks":null,"source_team":"T03C4RC8V","user_team":"T03C4RC8V"},{"client_msg_id":"f58fd58b-2eb8-4675-814c-d4395b27b7f3","type":"message","user":"U8996GYBF","text":"あ、両方入れてた場合もleximaがなければ問題なく、片方でもleximaで{を押した瞬間フリーズします","ts":"1535437525.000100","team":"T03C4RC8V","replace_original":false,"delete_original":false,"blocks":null,"source_team":"T03C4RC8V","user_team":"T03C4RC8V"},{"client_msg_id":"680d4455-d469-449f-bba4-9dce6fa3bc9a","type":"message","user":"U7JL1UKKL","text":"leximaで何が起こってるのかは気になる","ts":"1535437568.000100","team":"T03C4RC8V","replace_original":false,"delete_original":false,"blocks":null,"source_team":"T03C4RC8V","user_team":"T03C4RC8V"},{"client_msg_id":"0a7e5b69-1edd-4246-8eca-1b59809b1c09","type":"message","user":"U8996GYBF","text":"leximaのmappingが問題ではなくて `b:lexima_disabled = 1` で展開を無効にするだけで問題なくなっているところまでは確認しています","ts":"1535437583.000200","team":"T03C4RC8V","replace_original":false,"delete_original":false,"blocks":null,"source_team":"T03C4RC8V","user_team":"T03C4RC8V"},{"client_msg_id":"9a476c88-d243-4ff3-bbb5-b513c2600e65","type":"message","user":"U03C71D7H","text":"フリーズしたらどうすると復帰するのかな","ts":"1535437587.000100","team":"T03C4RC8V","replace_original":false,"delete_original":false,"blocks":null,"source_team":"T03C4RC8V","user_team":"T03C4RC8V"},{"client_msg_id":"c4ce7b03-48f3-478c-ae2f-f7b4cbe84406","type":"message","user":"U8996GYBF","text":"プロセス落としてますね・・・","ts":"1535437596.000100","team":"T03C4RC8V","replace_original":false,"delete_original":false,"blocks":null,"source_team":"T03C4RC8V","user_team":"T03C4RC8V"},{"client_msg_id":"03596d5e-c0d0-477a-af47-6f1db2625e8c","type":"message","user":"U03C71D7H","text":"&lt;C-c&gt; すら効かない?","ts":"1535437609.000100","team":"T03C4RC8V","replace_original":false,"delete_original":false,"blocks":null,"source_team":"T03C4RC8V","user_team":"T03C4RC8V"},{"client_msg_id":"5e42e340-b458-47af-8a0f-ec8551b8de99","type":"message","user":"U8996GYBF","text":"neovimでやってますが効かないです、あとでkillしたときに出るログがあったはずなので貼ってみます","ts":"1535437636.000100","team":"T03C4RC8V","replace_original":false,"delete_original":false,"blocks":null,"source_team":"T03C4RC8V","user_team":"T03C4RC8V"},{"client_msg_id":"b65af580-be72-4e23-8daa-b5a95188dbb0","type":"message","user":"U03C71D7H","text":"単にスクリプトで無限ループ発生とかなら C-c で止まるはずなので、もっと別の何かか","ts":"1535437665.000100","team":"T03C4RC8V","replace_original":false,"delete_original":false,"blocks":null,"source_team":"T03C4RC8V","user_team":"T03C4RC8V"},{"client_msg_id":"b64ce291-d9a0-4a61-8ae6-f2da2585653a","type":"message","user":"U03C71D7H","text":"この画像 Shougo さんっぽくてとても良い <https://cdn-ak.f.st-hatena.com/images/fotolife/b/blog-media/20180820/20180820170458.jpg>","ts":"1535437747.000100","attachments":[{"fallback":"1800x1200px image","id":1,"image_url":"https://cdn-ak.f.st-hatena.com/images/fotolife/b/blog-media/20180820/20180820170458.jpg","blocks":null,"from_url":"https://cdn-ak.f.st-hatena.com/images/fotolife/b/blog-media/20180820/20180820170458.jpg","original_url":"https://cdn-ak.f.st-hatena.com/images/fotolife/b/blog-media/20180820/20180820170458.jpg"}],"team":"T03C4RC8V","reactions":[{"name":"laughing","count":1,"users":["U06BRP8VD"]},{"name":"v","count":2,"users":["U797GBCAK","U8CC7MDCL"]}],"replace_original":false,"delete_original":false,"blocks":null,"source_team":"T03C4RC8V","user_team":"T03C4RC8V"},{"client_msg_id":"eec9de68-5488-4fa9-b91c-fd764a18b1fb","type":"message","user":"U7JL1UKKL","text":"なぜかこの写真が使われていた…。","ts":"1535437796.000100","team":"T03C4RC8V","replace_original":false,"delete_original":false,"blocks":null,"source_team":"T03C4RC8V","user_team":"T03C4RC8V"},{"client_msg_id":"e03f7e1d-d5b6-47ac-8071-41a201053cf0","type":"message","user":"U7JL1UKKL","text":"Python側で固まるとC-cは効きません","ts":"1535437821.000100","team":"T03C4RC8V","replace_original":false,"delete_original":false,"blocks":null,"source_team":"T03C4RC8V","user_team":"T03C4RC8V"},{"client_msg_id":"66acd79e-d03d-46aa-a63e-9a854e195b5e","type":"message","user":"U03C71D7H","text":"挙動聞いた感じ lexima が怪しいけど、lexima は pure Vim script なんですよね。となると lexima はやはりただのトリガーなのかな","ts":"1535437874.000100","team":"T03C4RC8V","replace_original":false,"delete_original":false,"blocks":null,"source_team":"T03C4RC8V","user_team":"T03C4RC8V"},{"client_msg_id":"42578333-6cd8-49a1-ac6e-ed389c2af398","type":"message","user":"U7JL1UKKL","text":"leximaがテキスト変更することで","ts":"1535437989.000100","team":"T03C4RC8V","replace_original":false,"delete_original":false,"blocks":null,"source_team":"T03C4RC8V","user_team":"T03C4RC8V"},{"client_msg_id":"5374f1e9-7b3f-407f-bc19-3b177e7d22fe","type":"message","user":"U7CGPB4NR","text":"手がVになってる","ts":"1535437996.000100","team":"T03C4RC8V","replace_original":false,"delete_original":false,"blocks":null,"source_team":"T03C4RC8V","user_team":"T03C4RC8V"},{"client_msg_id":"647ec07d-56c6-4e79-b6e5-66fe2307f6bb","type":"message","user":"U7JL1UKKL","text":"変更を監視してるnvim-typescriptが動き、それにleximaが反応する？","ts":"1535438028.000100","team":"T03C4RC8V","replace_original":false,"delete_original":false,"blocks":null,"source_team":"T03C4RC8V","user_team":"T03C4RC8V"},{"client_msg_id":"f4c99c49-7c67-4aca-9a93-79fd478ab9c6","type":"message","user":"U7JL1UKKL","text":"lexima側からでも、どこで固まるかある程度は調べられる気がするなぁ","ts":"1535438060.000100","team":"T03C4RC8V","replace_original":false,"delete_original":false,"blocks":null,"source_team":"T03C4RC8V","user_team":"T03C4RC8V"},{"client_msg_id":"33a2116f-393d-47ac-90ec-af5f4ba67949","type":"message","user":"U8996GYBF","text":"以前はkillしたときにdeopleteのログが出ていた気がするけど確認できなくなっている","ts":"1535438084.000100","team":"T03C4RC8V","replace_original":false,"delete_original":false,"blocks":null,"source_team":"T03C4RC8V","user_team":"T03C4RC8V"},{"client_msg_id":"c69b5ac3-8846-415f-920e-b691f1333ffe","type":"message","user":"U7JL1UKKL","text":"b:lexima_disabledがあると、マッピング展開の途中で戻るルーチンになっていたので","ts":"1535438094.000100","team":"T03C4RC8V","replace_original":false,"delete_original":false,"blocks":null,"source_team":"T03C4RC8V","user_team":"T03C4RC8V"},{"client_msg_id":"86f6a046-6bf3-4e8a-bebb-15b0b0b2f91a","type":"message","user":"U7JL1UKKL","text":"その後が問題なのでしょう","ts":"1535438103.000200","team":"T03C4RC8V","replace_original":false,"delete_original":false,"blocks":null,"source_team":"T03C4RC8V","user_team":"T03C4RC8V"},{"client_msg_id":"1afea27d-6907-47c8-8655-bd4f352a5767","type":"message","user":"U8996GYBF","text":"lspが非同期で割り込むとかその辺ですかねぇ","ts":"1535438138.000100","team":"T03C4RC8V","replace_original":false,"delete_original":false,"blocks":null,"source_team":"T03C4RC8V","user_team":"T03C4RC8V"},{"client_msg_id":"4ea986fa-b6d5-4bd9-b6f6-c652eb8dbf41","type":"message","user":"U03C71D7H","text":"固まるのは lexima による展開が行われる前か後か","ts":"1535438148.000100","team":"T03C4RC8V","replace_original":false,"delete_original":false,"blocks":null,"source_team":"T03C4RC8V","user_team":"T03C4RC8V"},{"client_msg_id":"59c859b4-c5d4-4158-81e6-748699583955","type":"message","user":"U8996GYBF","text":"画面には{}と出た後ですね","ts":"1535438166.000100","team":"T03C4RC8V","replace_original":false,"delete_original":false,"blocks":null,"source_team":"T03C4RC8V","user_team":"T03C4RC8V"},{"client_msg_id":"993a7090-dba2-4e4f-ad7e-0cdae903bafc","type":"message","user":"U8996GYBF","text":"あっ","ts":"1535438460.000100","team":"T03C4RC8V","replace_original":false,"delete_original":false,"blocks":null,"source_team":"T03C4RC8V","user_team":"T03C4RC8V"},{"client_msg_id":"9f06e047-cf08-4d8c-94b5-cb053c69b818","type":"message","user":"U8996GYBF","text":"lspのサーバが起動してから十分に時間が経っていれば問題ないっぽい感じが","ts":"1535438491.000100","team":"T03C4RC8V","replace_original":false,"delete_original":false,"blocks":null,"source_team":"T03C4RC8V","user_team":"T03C4RC8V"},{"client_msg_id":"814f5172-346b-41b4-af7d-d5e80d77d71a","type":"message","user":"U8996GYBF","text":"`{}` の中でTypeScriptの補完が行われるコンテキストになるんですが、lspがプロジェクトを解析とかしているタイミングでleximaが展開して補完候補を出そうとしたときにフリーズする・・・？","ts":"1535438543.000100","team":"T03C4RC8V","replace_original":false,"delete_original":false,"blocks":null,"source_team":"T03C4RC8V","user_team":"T03C4RC8V"},{"client_msg_id":"36fc8a1c-e429-46c4-9b88-fcbe0f755566","type":"message","user":"U7JL1UKKL","text":"なるほど","ts":"1535438574.000100","team":"T03C4RC8V","replace_original":false,"delete_original":false,"blocks":null,"source_team":"T03C4RC8V","user_team":"T03C4RC8V"},{"client_msg_id":"bd42b38b-67ff-41c1-8adf-ba078455a9dd","type":"message","user":"U7JL1UKKL","text":"確かにあり得る","ts":"1535438579.000100","team":"T03C4RC8V","replace_original":false,"delete_original":false,"blocks":null,"source_team":"T03C4RC8V","user_team":"T03C4RC8V"},{"client_msg_id":"55fb71ee-6509-401c-9028-195b8b7362e8","type":"message","user":"U7JL1UKKL","text":"そこでフリーズするならlsp側の実装の問題となる可能性も","ts":"1535438605.000100","team":"T03C4RC8V","replace_original":false,"delete_original":false,"blocks":null,"source_team":"T03C4RC8V","user_team":"T03C4RC8V"},{"client_msg_id":"87410e97-742d-43e2-a704-3a42bf2e4819","type":"message","user":"U8996GYBF","text":"そうですね、書いててLSP側の補完の問題の気がしてきました","ts":"1535438625.000100","team":"T03C4RC8V","replace_original":false,"delete_original":false,"blocks":null,"source_team":"T03C4RC8V","user_team":"T03C4RC8V"},{"client_msg_id":"71b6f286-7904-4923-9a99-817c88406cac","type":"message","user":"U8996GYBF","text":"どこで止まってるのか特定したいなぁ","ts":"1535438632.000100","team":"T03C4RC8V","replace_original":false,"delete_original":false,"blocks":null,"source_team":"T03C4RC8V","user_team":"T03C4RC8V"},{"client_msg_id":"fe24b768-338b-4471-a4a5-2718940f0213","type":"message","user":"U7JL1UKKL","text":"lsp側のコードを見るしかないですね","ts":"1535438641.000100","team":"T03C4RC8V","replace_original":false,"delete_original":false,"blocks":null,"source_team":"T03C4RC8V","user_team":"T03C4RC8V"},{"client_msg_id":"8e3f209b-84ee-4531-8799-bd8b27da9621","type":"message","user":"U7JL1UKKL","text":"deopleteで止まるとすると","ts":"1535438652.000100","team":"T03C4RC8V","replace_original":false,"delete_original":false,"blocks":null,"source_team":"T03C4RC8V","user_team":"T03C4RC8V"},{"client_msg_id":"ee66f46b-5fbf-46e7-b1f3-64ed4b5385b2","type":"message","user":"U7JL1UKKL","text":"内部で呼んでるオムニ補完呼んでるはず","ts":"1535438666.000100","team":"T03C4RC8V","replace_original":false,"delete_original":false,"blocks":null,"source_team":"T03C4RC8V","user_team":"T03C4RC8V"},{"client_msg_id":"3a8f5a8f-f1db-4be6-974d-f1659f4cf522","type":"message","user":"U8996GYBF","text":"LanguageClident-neovimとnvim-typescriptの両方で起こるというのが気にはなるんですが、そのあたり重複してるのかもしれないですね","ts":"1535438682.000100","team":"T03C4RC8V","replace_original":false,"delete_original":false,"blocks":null,"source_team":"T03C4RC8V","user_team":"T03C4RC8V"},{"client_msg_id":"0b696502-614a-413c-a7f7-75b56d01c0a1","type":"message","user":"U7JL1UKKL","text":"そこの中身ならVim scriptだろうから","ts":"1535438682.000200","team":"T03C4RC8V","replace_original":false,"delete_original":false,"blocks":null,"source_team":"T03C4RC8V","user_team":"T03C4RC8V"},{"client_msg_id":"c3939c2b-f2e8-42b8-bd5b-266b81229f50","type":"message","user":"U7JL1UKKL","text":"解析はできるんじゃないかなと","ts":"1535438690.000100","team":"T03C4RC8V","replace_original":false,"delete_original":false,"blocks":null,"source_team":"T03C4RC8V","user_team":"T03C4RC8V"},{"client_msg_id":"0bc76300-2606-4977-89bd-70a228c3b37f","type":"message","user":"U7JL1UKKL","text":"どちらも本体のルーチンはVim scriptなんですよ","ts":"1535438711.000100","team":"T03C4RC8V","replace_original":false,"delete_original":false,"blocks":null,"source_team":"T03C4RC8V","user_team":"T03C4RC8V"},{"client_msg_id":"96784ce5-42e2-4817-bcfd-a40467b5a684","type":"message","user":"U7JL1UKKL","text":"sourceはオムニ補完呼ぶだけです","ts":"1535438723.000100","team":"T03C4RC8V","replace_original":false,"delete_original":false,"blocks":null,"source_team":"T03C4RC8V","user_team":"T03C4RC8V"},{"client_msg_id":"0bdffeb8-54ac-435b-9ed3-3338b03851af","type":"message","user":"U8996GYBF","text":"うーん、完全に止まるんじゃなくてエラーログが欲しい","ts":"1535438741.000100","team":"T03C4RC8V","replace_original":false,"delete_original":false,"blocks":null,"source_team":"T03C4RC8V","user_team":"T03C4RC8V"},{"client_msg_id":"d6db9da8-ade7-46f9-b097-5e1e3d60c366","type":"message","user":"U7JL1UKKL","text":"Vim scriptで止まってるならVim script内でロギングかな","ts":"1535438795.000100","team":"T03C4RC8V","replace_original":false,"delete_original":false,"blocks":null,"source_team":"T03C4RC8V","user_team":"T03C4RC8V"},{"client_msg_id":"ad913134-3fed-4971-b2f6-0d0e5e068798","type":"message","user":"U7JL1UKKL","text":"Python側ならPythonのログライブラリーが使えるんですけどね","ts":"1535438812.000100","team":"T03C4RC8V","replace_original":false,"delete_original":false,"blocks":null,"source_team":"T03C4RC8V","user_team":"T03C4RC8V"},{"client_msg_id":"18a5a0b2-0a4a-401c-97b6-77b78c1ead6b","type":"message","user":"U8996GYBF","text":"あとはdelimimateでしたっけ、試してみてあれなら問題なかった気がするんですよね","ts":"1535438837.000100","team":"T03C4RC8V","replace_original":false,"delete_original":false,"blocks":null,"source_team":"T03C4RC8V","user_team":"T03C4RC8V"},{"client_msg_id":"dc43ef90-a7fc-4362-95c2-3f21779aed9e","type":"message","user":"U7JL1UKKL","text":"Pythonから呼び出したVim scriptで固まってもフリーズはするはず","ts":"1535438845.000100","team":"T03C4RC8V","replace_original":false,"delete_original":false,"blocks":null,"source_team":"T03C4RC8V","user_team":"T03C4RC8V"},{"client_msg_id":"25378806-d33b-495e-a1e0-d242d73b15a6","type":"message","user":"U7JL1UKKL","text":"実装が違うからでしょうね","ts":"1535438856.000100","team":"T03C4RC8V","replace_original":false,"delete_original":false,"blocks":null,"source_team":"T03C4RC8V","user_team":"T03C4RC8V"},{"client_msg_id":"ff254af8-3f9b-4f85-9ba9-bff044144993","type":"message","user":"U8996GYBF","text":"leximaのロジックとの相性っぽい気もしてます、deopleteでそのタイミングで補完が呼び出されなかったら解決するかも？","ts":"1535438879.000200","team":"T03C4RC8V","replace_original":false,"delete_original":false,"blocks":null,"source_team":"T03C4RC8V","user_team":"T03C4RC8V"},{"client_msg_id":"2d9abd2c-cd46-4351-ab81-ff855767560c","type":"message","user":"U7JL1UKKL","text":"それはできますよ","ts":"1535438933.000100","team":"T03C4RC8V","replace_original":false,"delete_original":false,"blocks":null,"source_team":"T03C4RC8V","user_team":"T03C4RC8V"},{"client_msg_id":"2f02e8ee-0f19-4827-acc3-2457685d7341","type":"message","user":"U7JL1UKKL","text":"input_patternを上書きすればよい","ts":"1535438963.000100","team":"T03C4RC8V","replace_original":false,"delete_original":false,"blocks":null,"source_team":"T03C4RC8V","user_team":"T03C4RC8V"},{"client_msg_id":"302104d7-341d-4df0-b44f-7aa7a36f779d","type":"message","user":"U7JL1UKKL","text":"input_patternのタイミングでsourceが呼ばれます","ts":"1535438975.000100","team":"T03C4RC8V","replace_original":false,"delete_original":false,"blocks":null,"source_team":"T03C4RC8V","user_team":"T03C4RC8V"},{"client_msg_id":"e2e6466c-edc2-4ec9-a3aa-dc2309e44917","type":"message","user":"U7JL1UKKL","text":"lspは汎用性を高めるため毎回の入力でlspを呼ぶようにパターンをセットしてるはずです","ts":"1535439003.000100","team":"T03C4RC8V","replace_original":false,"delete_original":false,"blocks":null,"source_team":"T03C4RC8V","user_team":"T03C4RC8V"},{"client_msg_id":"14f19d43-792f-42af-a7bd-6177cd93fb4f","type":"message","user":"U8996GYBF","text":"あーなるほど","ts":"1535439022.000100","team":"T03C4RC8V","replace_original":false,"delete_original":false,"blocks":null,"source_team":"T03C4RC8V","user_team":"T03C4RC8V"},{"client_msg_id":"affb4714-5d15-4200-9d76-7e424636cecb","type":"message","user":"U8996GYBF","text":"2文字目以降みたいな正規表現にすればいいんですかね、python書いたことないですが・・・","ts":"1535439043.000100","team":"T03C4RC8V","replace_original":false,"delete_original":false,"blocks":null,"source_team":"T03C4RC8V","user_team":"T03C4RC8V"},{"client_msg_id":"09b05a08-f724-4f9b-822c-7a1b9b1c426d","type":"message","user":"U8996GYBF","text":"`g:deoplete#auto_complete_start_length` と勝手に揃えて欲しい気持ちが","ts":"1535439196.000100","team":"T03C4RC8V","replace_original":false,"delete_original":false,"blocks":null,"source_team":"T03C4RC8V","user_team":"T03C4RC8V"},{"client_msg_id":"783e4991-e2f6-4142-9fd5-f05e36970748","type":"message","user":"U8996GYBF","text":"うーんちゃんと読み込んでるっぽい後でもやっぱり死ぬなぁ","ts":"1535439841.000100","team":"T03C4RC8V","replace_original":false,"delete_original":false,"blocks":null,"source_team":"T03C4RC8V","user_team":"T03C4RC8V"},{"type":"message","user":"UCHD69E4F","text":"<@UCHD69E4F> has joined the channel","ts":"1535439867.000200","subtype":"channel_join","replace_original":false,"delete_original":false,"blocks":null},{"client_msg_id":"c1307fdd-f542-4118-9727-d026dafb6a0f","type":"message","user":"U8996GYBF","text":"&lt;BS&gt;を上書きしてるあたりもちょっと怪しいっぽいです","ts":"1535439885.000100","edited":{"user":"U8996GYBF","ts":"1535439892.000000"},"team":"T03C4RC8V","replace_original":false,"delete_original":false,"blocks":null,"source_team":"T03C4RC8V","user_team":"T03C4RC8V"},{"client_msg_id":"8eaa26cc-083a-48b9-86f3-414450edc7d0","type":"message","user":"U8996GYBF","text":"lexima使ってると死ぬタイミングで普通に同じコードで補完しても通るんだけど、なんでだろう・・・","ts":"1535440025.000100","team":"T03C4RC8V","replace_original":false,"delete_original":false,"blocks":null,"source_team":"T03C4RC8V","user_team":"T03C4RC8V"},{"client_msg_id":"55c00def-fea9-4136-855b-4972f6a96846","type":"message","user":"U8996GYBF","text":"leximaが言語毎にあるのとないのでコード書くの結構疲れるんですよね、うーん","ts":"1535440210.000100","team":"T03C4RC8V","replace_original":false,"delete_original":false,"blocks":null,"source_team":"T03C4RC8V","user_team":"T03C4RC8V"},{"client_msg_id":"e122a323-7ccf-4858-8032-1611d2bc7ea1","type":"message","user":"U03C4RC8X","text":"leximaぽいのをvim本体でできるようにして、&lt;cr&gt;とか&lt;bs&gt;とかを上書きしなくてもいいようにできるといろんなプラギンとの相性がよくなったりするかなあ","ts":"1535443165.000200","team":"T03C4RC8V","replace_original":false,"delete_original":false,"blocks":null,"source_team":"T03C4RC8V","user_team":"T03C4RC8V"},{"type":"message","user":"UCG7133S8","text":"<@UCG7133S8> has joined the channel","ts":"1535446211.000200","subtype":"channel_join","replace_original":false,"delete_original":false,"blocks":null},{"client_msg_id":"83a724e0-8def-44fb-a495-caf0c6f6d2ba","type":"message","user":"U9GUS1S0G","text":"smartinput の設定をたくさん書いていると自動補完と相性わるいな、と思ったことは結構あった気がする\n自動入力中にも補完しようとしてちょっと固まる、みたいな感じだったかな","ts":"1535449772.000100","team":"T03C4RC8V","replace_original":false,"delete_original":false,"blocks":null,"source_team":"T03C4RC8V","user_team":"T03C4RC8V"},{"client_msg_id":"9de923cb-66f3-4f13-9d8e-3664ec5d5528","type":"message","user":"U9GUS1S0G","text":"自動入力中だけ補完を止めたい","ts":"1535449838.000100","team":"T03C4RC8V","replace_original":false,"delete_original":false,"blocks":null,"source_team":"T03C4RC8V","user_team":"T03C4RC8V"},{"client_msg_id":"8d3f6226-4f81-4201-b7c4-68c79dd7a185","type":"message","user":"U7JL1UKKL","text":"プラグイン側でその入力変化がユーザーによるものなのかわからないと無理なのですよね","ts":"1535450236.000100","team":"T03C4RC8V","replace_original":false,"delete_original":false,"blocks":null,"source_team":"T03C4RC8V","user_team":"T03C4RC8V"},{"client_msg_id":"9ae48d64-dcae-414f-9182-1f8db3c9830a","type":"message","user":"U7JL1UKKL","text":"自動的に止めるというのは","ts":"1535450254.000100","team":"T03C4RC8V","replace_original":false,"delete_original":false,"blocks":null,"source_team":"T03C4RC8V","user_team":"T03C4RC8V"},{"client_msg_id":"df1a2a94-c8b6-4974-935f-03e85413d3fd","type":"message","user":"U9GUS1S0G","text":"自動入力プラグイン側が入力前後に autocmd イベントを定義してくれたらユーザーがなんとかできると思うんですよね","ts":"1535450520.000100","team":"T03C4RC8V","replace_original":false,"delete_original":false,"blocks":null,"source_team":"T03C4RC8V","user_team":"T03C4RC8V"},{"client_msg_id":"9c2a980b-5058-4891-a77b-6d7ff98914d0","type":"message","user":"U9GUS1S0G","text":"```\nautocmd User SmartinputPre :{なにか自動補完を一時停止するコマンド}\nautocmd User SmartinputPost :{なにか自動補完を再開するコマンド}\n```\nみたいなイメージ。呼ばれすぎるというのが問題なんですけど。","ts":"1535450725.000100","team":"T03C4RC8V","replace_original":false,"delete_original":false,"blocks":null,"source_team":"T03C4RC8V","user_team":"T03C4RC8V"},{"client_msg_id":"0aaf8bce-346b-474b-ad5e-31bf3b121f3d","type":"message","user":"U7JL1UKKL","text":"なるほど","ts":"1535452329.000100","team":"T03C4RC8V","replace_original":false,"delete_original":false,"blocks":null,"source_team":"T03C4RC8V","user_team":"T03C4RC8V"},{"client_msg_id":"f33f368e-04d8-42d0-a101-03d45111779c","type":"message","user":"U7JL1UKKL","text":"set pasteみたいなものですね","ts":"1535452344.000100","team":"T03C4RC8V","replace_original":false,"delete_original":false,"blocks":null,"source_team":"T03C4RC8V","user_team":"T03C4RC8V"},{"client_msg_id":"494053ab-bc7d-4a33-a195-ffebb96bb23b","type":"message","user":"U9GUS1S0G","text":"まさにそんな感じです","ts":"1535454990.000100","team":"T03C4RC8V","replace_original":false,"delete_original":false,"blocks":null,"source_team":"T03C4RC8V","user_team":"T03C4RC8V"},{"client_msg_id":"60c642d8-6dac-4acd-849b-eb11e3933292","type":"message","user":"U9GUS1S0G","text":"いつの間にか、 `.` コマンドが関数の中でも動くようになっている…","ts":"1535455045.000100","team":"T03C4RC8V","replace_original":false,"delete_original":false,"blocks":null,"source_team":"T03C4RC8V","user_team":"T03C4RC8V"},{"client_msg_id":"bcb15b2c-dede-437a-8255-b6dec8cc795c","type":"message","user":"U9GUS1S0G","text":"<https://github.com/vim/vim/commit/d4863aa99e0527e9505c79cbeafc68a6832200bf>","ts":"1535456929.000100","attachments":[{"fallback":"GitHub: patch 8.0.0548: saving the redo buffer only works one time · vim/vim@d4863aa","id":1,"title":"patch 8.0.0548: saving the redo buffer only works one time · vim/vim@d4863aa","title_link":"https://github.com/vim/vim/commit/d4863aa99e0527e9505c79cbeafc68a6832200bf","text":"Problem: Saving the redo buffer only works one time, resulting in the &amp;quot;.&amp;quot; command not working well for a function call inside another function call. (Ingo Karka...","thumb_url":"https://avatars1.githubusercontent.com/u/8530623?s=200&v=4","blocks":null,"service_name":"GitHub","service_icon":"https://a.slack-edge.com/bfaba/img/unfurl_icons/github.png","thumb_width":200,"thumb_height":200,"from_url":"https://github.com/vim/vim/commit/d4863aa99e0527e9505c79cbeafc68a6832200bf","original_url":"https://github.com/vim/vim/commit/d4863aa99e0527e9505c79cbeafc68a6832200bf"}],"edited":{"user":"U9GUS1S0G","ts":"1535456954.000000"},"team":"T03C4RC8V","replace_original":false,"delete_original":false,"blocks":null,"source_team":"T03C4RC8V","user_team":"T03C4RC8V"},{"client_msg_id":"a73e79d4-5582-437b-854f-6514492cfa50","type":"message","user":"U9GUS1S0G","text":"一年以上前だった…\n`.` コマンドのテストが捗る","ts":"1535456964.000100","team":"T03C4RC8V","replace_original":false,"delete_original":false,"blocks":null,"source_team":"T03C4RC8V","user_team":"T03C4RC8V"},{"client_msg_id":"8EA0B2A7-3BA8-4CA2-84A9-DED5CD02D094","type":"message","user":"U8996GYBF","text":"smartinputで死なないならTypeScript書くときだけそっちに無理矢理切り替えるのもありだなぁ、明日試してみよう","ts":"1535466118.000100","team":"T03C4RC8V","replace_original":false,"delete_original":false,"blocks":null,"source_team":"T03C4RC8V","user_team":"T03C4RC8V"},{"client_msg_id":"62E179F3-AF27-413C-BFCD-F9C8CE66BDC5","type":"message","user":"U8996GYBF","text":"leximaで入力の前後に特定の関数を呼ぶ仕組み入れる、でも解決するのかな Multiple_cursors_before 的な","ts":"1535466365.000100","team":"T03C4RC8V","replace_original":false,"delete_original":false,"blocks":null,"source_team":"T03C4RC8V","user_team":"T03C4RC8V"},{"client_msg_id":"10F21DEB-3937-446E-81BE-E595DD9CCA2C","type":"message","user":"U8996GYBF","text":"forkして試してみるとよさそうかも？\n大半が記号入力時の展開だからその瞬間に補完が動いて欲しいことはあまりなさそうな気が","ts":"1535466429.000100","team":"T03C4RC8V","replace_original":false,"delete_original":false,"blocks":null,"source_team":"T03C4RC8V","user_team":"T03C4RC8V"},{"client_msg_id":"3B138E6D-931D-4A0C-8087-B05A87BFA0D9","type":"message","user":"U8996GYBF","text":"&lt;BS&gt;したときに補完が出なくなるのが不便そうくらいですかねぇ","ts":"1535466532.000100","team":"T03C4RC8V","replace_original":false,"delete_original":false,"blocks":null,"source_team":"T03C4RC8V","user_team":"T03C4RC8V"}]
