[{"type":"message","ts":"1507804695.000430","attachments":[{"fallback":"\n\npatch 8.0.1185: Ruby library includes minor version number\n\nProblem:    Ruby library includes minor version number.\nSolution:   Only use the API version number. (Ben Boeckel, closes #2199)\n","title":"patch 8.0.1185: Ruby library includes minor version number","title_link":"https://github.com/vim/vim/commit/9202162c5c069c925b6b9bf84e546fbd362cdf46","text":"\n\npatch 8.0.1185: Ruby library includes minor version number\n\nProblem:    Ruby library includes minor version number.\nSolution:   Only use the API version number. (Ben Boeckel, closes #2199)\n","thumb_url":"https://ifttt.com/images/no_image_card.png","mrkdwn_in":["text","pretext"],"blocks":null,"thumb_width":800,"thumb_height":494}],"subtype":"bot_message","bot_id":"B0VCFSN5C","username":"IFTTT","icons":{"image_48":"https://a.slack-edge.com/8f51/img/services/ifttt_48.png"},"replace_original":false,"delete_original":false,"blocks":null},{"type":"message","user":"U7CF6G47L","text":"<@U7CF6G47L> has joined the channel","ts":"1507771354.000094","subtype":"channel_join","replace_original":false,"delete_original":false,"blocks":null},{"type":"message","user":"U03C6TEAZ","text":"<@U03C6TEAZ> has joined the channel","ts":"1507774659.000053","subtype":"channel_join","replace_original":false,"delete_original":false,"blocks":null},{"type":"message","user":"U7AMBEEG0","text":"<@U7AMBEEG0> has joined the channel","ts":"1507775319.000100","subtype":"channel_join","replace_original":false,"delete_original":false,"blocks":null},{"type":"message","user":"U0M7GCBPD","text":"<@U0M7GCBPD> has joined the channel","ts":"1507776434.000113","subtype":"channel_join","replace_original":false,"delete_original":false,"blocks":null}]
