[{"client_msg_id":"9ee6abe2-322a-43f2-9a21-9bd6155ce87b","type":"message","user":"U03C4RC8X","text":"asakusa.vim開場で宣伝できそう","ts":"1543689524.001100","team":"T03C4RC8V","replace_original":false,"delete_original":false,"blocks":null,"source_team":"T03C4RC8V","user_team":"T03C4RC8V"},{"client_msg_id":"927daae2-7ced-4f52-8c13-07d7b63e8dfa","type":"message","user":"U782D5DF1","text":"8日にmeguro.vim, 9日にsibuyaku-lisp, 連日はだるい・・・","ts":"1543689642.001800","team":"T03C4RC8V","replace_original":false,"delete_original":false,"blocks":null,"source_team":"T03C4RC8V","user_team":"T03C4RC8V"}]
