[{"client_msg_id":"be607a77-fb05-45a0-9443-c4fa76787282","type":"message","user":"U8996GYBF","text":"markのz使うんですね、なるほど","ts":"1609509216.360900","team":"T03C4RC8V","replace_original":false,"delete_original":false,"blocks":[{"type":"rich_text","block_id":"dlQ"}]},{"client_msg_id":"15d75b86-38d3-44c6-8838-577773acaa37","type":"message","user":"U01D9BALEKU","text":"語頭だけ大文字小文字入れ替え","ts":"1609508955.360400","team":"T03C4RC8V","replace_original":false,"delete_original":false,"blocks":[{"type":"rich_text","block_id":"78GM"}]},{"client_msg_id":"196d1800-dbb8-4bf8-8698-f979331c127a","type":"message","user":"U01D9BALEKU","text":"ちなみにこんなことしてました\n`nnoremap \u0026lt;Leader\u0026gt;` mz\"zyiwg~l`z`","ts":"1609508936.360000","team":"T03C4RC8V","replace_original":false,"delete_original":false,"blocks":[{"type":"rich_text","block_id":"WdH"}]},{"client_msg_id":"fc1ffd1f-3da7-4fbc-9efc-be6347f4eb57","type":"message","user":"U01D9BALEKU","text":"でも全部変わるのはそれはそれで感あるな\nまあ後で考えるか。。。","ts":"1609508907.359700","team":"T03C4RC8V","replace_original":false,"delete_original":false,"blocks":[{"type":"rich_text","block_id":"=Rhm"}]},{"client_msg_id":"8e116afa-e2a9-4805-be7d-aba5dfa3a8d3","type":"message","user":"U01D9BALEKU","text":"`nnoremap y myy` とかとりあえず入れてた","ts":"1609508880.359000","team":"T03C4RC8V","replace_original":false,"delete_original":false,"blocks":[{"type":"rich_text","block_id":"=Vw"}]},{"client_msg_id":"98505429-3805-4dd7-857b-bb88b32b9ba8","type":"message","user":"U01D9BALEKU","text":"いやそれはそれでしたかったですｗ","ts":"1609508862.358600","team":"T03C4RC8V","replace_original":false,"delete_original":false,"blocks":[{"type":"rich_text","block_id":"qkX"}]},{"client_msg_id":"fe319c58-93e6-42d9-ad5f-a167efed6ab5","type":"message","user":"U8996GYBF","text":"飛ぶことを使ったマップか、飛ばないようにしたいのかと勘違いしてました\nすみません","ts":"1609508846.358300","team":"T03C4RC8V","replace_original":false,"delete_original":false,"blocks":[{"type":"rich_text","block_id":"rs5i"}]},{"client_msg_id":"0da1d6eb-f61b-4668-81aa-f6922f139104","type":"message","user":"U01D9BALEKU","text":"この記事はこの記事でありがたいです","ts":"1609508826.357900","team":"T03C4RC8V","replace_original":false,"delete_original":false,"blocks":[{"type":"rich_text","block_id":"LZ6"}]},{"client_msg_id":"f5642020-e518-4e9d-b8aa-3017e5f2b965","type":"message","user":"U01D9BALEKU","text":"っていうか大きくヤンクしたときに動いて見失っちゃうことに気づいて思いついたんですよね","ts":"1609508814.357600","team":"T03C4RC8V","replace_original":false,"delete_original":false,"blocks":[{"type":"rich_text","block_id":"SlC9g"}]},{"client_msg_id":"c54eed0d-da0f-4c9d-8e88-674d396b77f6","type":"message","user":"U01D9BALEKU","text":"おー","ts":"1609508787.357000","team":"T03C4RC8V","replace_original":false,"delete_original":false,"blocks":[{"type":"rich_text","block_id":"9si"}]},{"client_msg_id":"c27c60e0-783e-481e-8a17-90f76795cfa9","type":"message","user":"U8996GYBF","text":"textobjというかoperatorの操作で先頭か","ts":"1609508778.356700","team":"T03C4RC8V","replace_original":false,"delete_original":false,"blocks":[{"type":"rich_text","block_id":"y1W"}]},{"client_msg_id":"b7ab9098-dbff-4465-9155-38097c569107","type":"message","user":"U8996GYBF","text":"\u003chttps://secret-garden.hatenablog.com/entry/2015/03/18/232847\u003e\nこんなのがあります、記憶辿ったらすぐ見つけられた","ts":"1609508757.356300","attachments":[{"fallback":"Secret Garden(Instrumental): Vim で operator 実行時にカーソルを移動させないような operator をつくった - Secret Garden(Instrumental)","id":1,"title":"Vim で operator 実行時にカーソルを移動させないような operator をつくった - Secret Garden(Instrumental)","title_link":"https://secret-garden.hatenablog.com/entry/2015/03/18/232847","text":"さて、Vim で operator を実行するとカーソル位置が入力した motion の先頭へと移動してしまします。 これは c や d のようなバッファを変更する operator であれば便利なんですが、y などのバッファを変更しない operator であれば無駄にカーソルが移動してしまうだけなので不便と感じる事があります。 と、いうことで任意の operator の実行時にカーソルを移動させないようにするラッパー operator をつくりました。 [プラグイン] osyo-manga/vim-operator-stay-cursor kana/vim-operator-user Ne…","image_url":"https://ogimage.blog.st-hatena.com/8454420450083857220/8454420450088532785/1426688927","blocks":null,"ts":1426688927,"service_name":"Secret Garden(Instrumental)","service_icon":"https://secret-garden.hatenablog.com/icon/touch","from_url":"https://secret-garden.hatenablog.com/entry/2015/03/18/232847","original_url":"https://secret-garden.hatenablog.com/entry/2015/03/18/232847"}],"team":"T03C4RC8V","replace_original":false,"delete_original":false,"blocks":[{"type":"rich_text","block_id":"pZI"}]},{"client_msg_id":"6526fbd5-ae6a-4bd8-bcd3-803086bd9425","type":"message","user":"U8996GYBF","text":"テキストオブジェクトを操作したときにその先頭に飛ぶのは一般的な挙動ですね","ts":"1609508719.355800","team":"T03C4RC8V","reactions":[{"name":"eyes","count":1,"users":["U01D9BALEKU"]}],"replace_original":false,"delete_original":false,"blocks":[{"type":"rich_text","block_id":"cFKZ"}]},{"client_msg_id":"c99c2b3a-1320-42d1-a2a9-f195df77145c","type":"message","user":"U01D9BALEKU","text":"`yiw` でカーソルが語頭に飛ぶことを使ったマップを書いたんですが、いまの環境でたまたまそうなってるのか、そういう物なのか気になりました","ts":"1609508651.355300","team":"T03C4RC8V","replace_original":false,"delete_original":false,"blocks":[{"type":"rich_text","block_id":"5ebY"}]},{"client_msg_id":"3d8387e8-0350-47c2-b150-5dd2b48693e3","type":"message","user":"U01D9BALEKU","text":"テキストオブジェクトをヤンクしたときにカーソルが先頭に行くのって変更可能な動きでしょうか？","ts":"1609508537.354300","team":"T03C4RC8V","replace_original":false,"delete_original":false,"blocks":[{"type":"rich_text","block_id":"8FZUP"}]},{"client_msg_id":"7d966f1e-2041-48f8-9922-12055c3b4dd9","type":"message","user":"U01D9BALEKU","text":"あけましておめでとうございます","ts":"1609508509.353800","team":"T03C4RC8V","replace_original":false,"delete_original":false,"blocks":[{"type":"rich_text","block_id":"ykq"}]},{"client_msg_id":"73421f91-bc5a-46c6-88f2-6fd2703a82b5","type":"message","user":"U6XP9LZ6V","text":"vim-jp/vim は開発作業用の \u003chttps://github.com/vim/vim\u003e の単なる clone です。","ts":"1609497048.353400","attachments":[{"fallback":"GitHub: vim/vim","id":1,"title":"vim/vim","title_link":"https://github.com/vim/vim","text":"The official Vim repository. Contribute to vim/vim development by creating an account on GitHub.","thumb_url":"https://avatars0.githubusercontent.com/u/11618545?s=400\u0026v=4","blocks":null,"service_name":"GitHub","service_icon":"https://a.slack-edge.com/80588/img/unfurl_icons/github.png","thumb_width":48,"thumb_height":48,"from_url":"https://github.com/vim/vim","original_url":"https://github.com/vim/vim"}],"team":"T03C4RC8V","replace_original":false,"delete_original":false,"blocks":[{"type":"rich_text","block_id":"9Ytr"}]},{"client_msg_id":"686e71f4-7566-4d9e-9bc0-fa1982ca94f4","type":"message","user":"U6XP9LZ6V","text":"\u003chttps://github.com/vim/vim-win32-installer/blob/master/appveyor.bat\u003e です。","ts":"1609496783.351700","attachments":[{"fallback":"GitHub: vim/vim-win32-installer","id":1,"title":"vim/vim-win32-installer","title_link":"https://github.com/vim/vim-win32-installer/blob/master/appveyor.bat","text":"Vim Win32 Installer. Contribute to vim/vim-win32-installer development by creating an account on GitHub.","thumb_url":"https://avatars0.githubusercontent.com/u/11618545?s=400\u0026v=4","blocks":null,"service_name":"GitHub","service_icon":"https://a.slack-edge.com/80588/img/unfurl_icons/github.png","thumb_width":48,"thumb_height":48,"from_url":"https://github.com/vim/vim-win32-installer/blob/master/appveyor.bat","original_url":"https://github.com/vim/vim-win32-installer/blob/master/appveyor.bat"}],"team":"T03C4RC8V","reactions":[{"name":"+1","count":1,"users":["U797F1QK1"]}],"replace_original":false,"delete_original":false,"blocks":[{"type":"rich_text","block_id":"Iny"}]},{"client_msg_id":"f4fae869-a4f1-4560-b015-32f96f3a02ad","type":"message","user":"U797F1QK1","text":"\u003chttps://vim-jp.org/\u003e の vim-win32-installer のビルドを行うスクリプトって\n\u003chttps://github.com/vim-jp/vim/blob/master/ci/appveyor.bat\u003e でしょうか?\nconda-forgeというパッケージリポジトリ用に同様の(g)vimのパッケージを作りたいと思っています","ts":"1609492032.351100","attachments":[{"fallback":"vim-jp.github.io: Vimのユーザーと開発者を結ぶコミュニティサイト","id":1,"title":"Vimのユーザーと開発者を結ぶコミュニティサイト","title_link":"https://vim-jp.org/","text":"The website for \u003chttp://vim-jp.org|vim-jp.org\u003e","thumb_url":"https://vim-jp.org/assets/images/vim2-128.png","blocks":null,"service_name":"vim-jp.github.io","service_icon":"https://vim-jp.org/favicon.ico","thumb_width":128,"thumb_height":128,"from_url":"https://vim-jp.org/","original_url":"https://vim-jp.org/"},{"fallback":"GitHub: vim-jp/vim","id":2,"title":"vim-jp/vim","title_link":"https://github.com/vim-jp/vim/blob/master/ci/appveyor.bat","text":"vim-jp's collaboration workspace (clone of vim/vim) - vim-jp/vim","thumb_url":"https://avatars2.githubusercontent.com/u/1051958?s=400\u0026v=4","blocks":null,"service_name":"GitHub","service_icon":"https://a.slack-edge.com/80588/img/unfurl_icons/github.png","thumb_width":400,"thumb_height":400,"from_url":"https://github.com/vim-jp/vim/blob/master/ci/appveyor.bat","original_url":"https://github.com/vim-jp/vim/blob/master/ci/appveyor.bat"}],"team":"T03C4RC8V","replace_original":false,"delete_original":false,"blocks":[{"type":"rich_text","block_id":"MB7v"}]},{"type":"message","user":"U01HV7LPZA6","text":"\u003c@U01HV7LPZA6\u003e has joined the channel","ts":"1609479508.349000","subtype":"channel_join","replace_original":false,"delete_original":false,"blocks":null},{"type":"message","user":"U01J7703PFT","text":"\u003c@U01J7703PFT\u003e has joined the channel","ts":"1609429439.348800","subtype":"channel_join","replace_original":false,"delete_original":false,"blocks":null},{"client_msg_id":"e820b544-1c49-4387-a27b-6680c8b93a30","type":"message","user":"U7JL1UKKL","text":"それはPython3.8でビルドされていますね","ts":"1609426962.348500","team":"T03C4RC8V","reactions":[{"name":"+1","count":1,"users":["U797F1QK1"]}],"replace_original":false,"delete_original":false,"blocks":[{"type":"rich_text","block_id":"N=6kO"}]}]
