[{"client_msg_id":"3a4fcc3d-4a1a-46fe-b842-f0a0767b6b3c","type":"message","user":"UAUFDS92N","text":"ついにリングフィットの購入に成功しました\n\u003chttps://twitter.com/higashi136_2/status/1325272339173449728?s=19|https://twitter.com/higashi136_2/status/1325272339173449728?s=19\u003e","ts":"1604804550.371400","attachments":[{"fallback":"\u003chttps://twitter.com/higashi136_2|@higashi136_2\u003e: リングフィット届いた！！ \u003chttps://pbs.twimg.com/media/EmRQKuhU8AEInBu.jpg\u003e","id":1,"author_name":"higashi","author_subname":"@higashi136_2","author_link":"https://twitter.com/higashi136_2/status/1325272339173449728","author_icon":"https://pbs.twimg.com/profile_images/1245574028145774595/St7j-XfL_normal.jpg","text":"リングフィット届いた！！ \u003chttps://pbs.twimg.com/media/EmRQKuhU8AEInBu.jpg\u003e","image_url":"https://pbs.twimg.com/media/EmRQKuhU8AEInBu.jpg","blocks":null,"footer":"Twitter","footer_icon":"https://a.slack-edge.com/80588/img/services/twitter_pixel_snapped_32.png","ts":1604804522,"service_name":"twitter","from_url":"https://twitter.com/higashi136_2/status/1325272339173449728?s=19","original_url":"https://twitter.com/higashi136_2/status/1325272339173449728?s=19"}],"team":"T03C4RC8V","reactions":[{"name":"goodpoem","count":9,"users":["U9S4G0LJW","U06BRP8VD","U017BU3UZBQ","UD1FQV38V","U7JL1UKKL","U03C71D7H","UQX22KG9F","UBRTB4N5C","U01CMDFG4P7"]},{"name":"rotate-inochinokagayaki","count":2,"users":["U9S4G0LJW","UK0JC4CM8"]}],"replace_original":false,"delete_original":false,"blocks":[{"type":"rich_text","block_id":"f9Ekc"}]}]
