[{"client_msg_id":"bbfada58-abca-455a-b9f8-861c6f4fe459","type":"message","user":"UA45QC3NE","text":"今週の後半に上手いことどうのこうのと言っておりましたが、今日（土曜）から富士山に向かうので改めることになります。来週頑張る。","ts":"1530293070.000218","team":"T03C4RC8V","replace_original":false,"delete_original":false,"blocks":null,"source_team":"T03C4RC8V","user_team":"T03C4RC8V"},{"client_msg_id":"ce958043-f6bb-42e4-b9ea-c596a42e374a","type":"message","user":"U03C4RC8X","text":"おお、富士山","ts":"1530315416.000010","team":"T03C4RC8V","replace_original":false,"delete_original":false,"blocks":null,"source_team":"T03C4RC8V","user_team":"T03C4RC8V"},{"client_msg_id":"667a6bea-4787-461a-8fa0-1d5aaecd4efd","type":"message","user":"U03C4RC8X","text":"3000m超これか","ts":"1530315433.000041","team":"T03C4RC8V","replace_original":false,"delete_original":false,"blocks":null,"source_team":"T03C4RC8V","user_team":"T03C4RC8V"},{"client_msg_id":"ffab9040-48e7-4f67-b58a-693f1e5fac6d","type":"message","user":"UA45QC3NE","text":"とりあえず富士山に出る直前に釣りに出掛けたけど、はっきり言って釣れるわけがないのだった。","ts":"1530319454.000015","team":"T03C4RC8V","replace_original":false,"delete_original":false,"blocks":null,"source_team":"T03C4RC8V","user_team":"T03C4RC8V"},{"client_msg_id":"e7ed5f4d-3325-4b90-99c1-b90166cf4dfa","type":"message","user":"UA45QC3NE","text":"うちから歩いてすぐのところは人間が多すぎる。渓流釣りの一大スポットだしもう 6 月なので魚がスレまくってる。","ts":"1530319486.000068","team":"T03C4RC8V","replace_original":false,"delete_original":false,"blocks":null,"source_team":"T03C4RC8V","user_team":"T03C4RC8V"},{"client_msg_id":"85251a6f-fa0f-4917-bda4-1c0060ae09d7","type":"message","user":"UA45QC3NE","text":"1.5 時間やってボウズ。","ts":"1530319496.000020","team":"T03C4RC8V","replace_original":false,"delete_original":false,"blocks":null,"source_team":"T03C4RC8V","user_team":"T03C4RC8V"},{"client_msg_id":"f16da4cb-fc2f-423f-98fd-e67cb13dc9f9","type":"message","user":"UA45QC3NE","text":"ムカついたのでオタマジャクシと、足が生えてギリギリ蛙っぽくなったオタマジャクシを大量に捕まえてきた。後で煮て食う。","ts":"1530319519.000101","team":"T03C4RC8V","replace_original":false,"delete_original":false,"blocks":null,"source_team":"T03C4RC8V","user_team":"T03C4RC8V"},{"client_msg_id":"4d5edd44-ac99-4876-88d1-fce938af4d14","type":"message","user":"UA45QC3NE","text":"食ったら富士山行く。","ts":"1530319522.000038","team":"T03C4RC8V","replace_original":false,"delete_original":false,"blocks":null,"source_team":"T03C4RC8V","user_team":"T03C4RC8V"},{"client_msg_id":"00204962-22c7-4658-b0e6-f918a6c29343","type":"message","user":"U03C4RC8X","text":"ボウズつらそう","ts":"1530320819.000075","team":"T03C4RC8V","replace_original":false,"delete_original":false,"blocks":null,"source_team":"T03C4RC8V","user_team":"T03C4RC8V"},{"client_msg_id":"18d76311-8d20-45fb-982e-4377f141fd42","type":"message","user":"U03C4RC8X","text":"オタマジャクシよさそう","ts":"1530320836.000032","team":"T03C4RC8V","replace_original":false,"delete_original":false,"blocks":null,"source_team":"T03C4RC8V","user_team":"T03C4RC8V"},{"client_msg_id":"64fb79ce-f759-4cbd-8cfc-7e387b62d5f8","type":"message","user":"U03C4RC8X","text":"どぜうみたいな感じかなと推測","ts":"1530320840.000058","team":"T03C4RC8V","replace_original":false,"delete_original":false,"blocks":null,"source_team":"T03C4RC8V","user_team":"T03C4RC8V"}]
