[{"client_msg_id":"a9c459fa-a288-4300-98d1-d58939338e48","type":"message","user":"U9S4G0LJW","text":"実は末尾に日本語が入ってるせいでYouTubeが動画を日本語判定していて字幕がデタラメ日本語になっているというバグがある","ts":"1613831869.003800","team":"T03C4RC8V","replace_original":false,"delete_original":false,"blocks":[{"type":"rich_text","block_id":"UTp/h"}]},{"client_msg_id":"47ab1f5f-9322-41e3-9d75-147e43288199","type":"message","user":"U03C6TEAZ","text":"Not tell your doller all. (デタラメ英語)","ts":"1613831803.002900","team":"T03C4RC8V","reactions":[{"name":"fuita","count":2,"users":["U9S4G0LJW","UAZ33BKV2"]}],"replace_original":false,"delete_original":false,"blocks":[{"type":"rich_text","block_id":"I2O"}]},{"client_msg_id":"337bfde5-1f50-418a-934d-ebec5fe76732","type":"message","user":"U03C6TEAZ","text":"実は英語の可能性。","ts":"1613831768.002100","team":"T03C4RC8V","reactions":[{"name":"fukaikousatsu","count":1,"users":["U9S4G0LJW"]}],"replace_original":false,"delete_original":false,"blocks":[{"type":"rich_text","block_id":"Gv="}]},{"client_msg_id":"b175279c-3fac-4d24-a004-35d8003841c3","type":"message","user":"U9S4G0LJW","text":"流暢な英語の隙間に「なんていうんだろう（日本語）」が挟まるシーンが面白い（注目すべき場所じゃない）","ts":"1613795553.001300","team":"T03C4RC8V","reactions":[{"name":"eyes","count":1,"users":["U81LLJ340"]}],"replace_original":false,"delete_original":false,"blocks":[{"type":"rich_text","block_id":"nWzsA"}]},{"client_msg_id":"40618b9b-1790-4629-85e0-1edfe72a677c","type":"message","user":"U9S4G0LJW","text":"これ見てる \u003chttps://www.youtube.com/watch?v=zkANQ9l7YDM\u0026amp;list=PLx8bw5NQypskGEy8ARntIDxKmXcBEoRZQ\u0026amp;index=10\u003e","ts":"1613795513.000400","attachments":[{"fallback":"YouTube Video: You've been Super Viman. After this talk, you could say you are Super Viman 2 - Life with gina.vim","id":1,"author_name":"vim-jp","author_link":"https://www.youtube.com/c/Vim-jpOrg","title":"You've been Super Viman. After this talk, you could say you are Super Viman 2 - Life with gina.vim","title_link":"https://www.youtube.com/watch?v=zkANQ9l7YDM\u0026amp;index=10","thumb_url":"https://i.ytimg.com/vi/zkANQ9l7YDM/hqdefault.jpg","blocks":null,"service_name":"YouTube","service_icon":"https://a.slack-edge.com/80588/img/unfurl_icons/youtube.png","thumb_width":480,"thumb_height":360,"video_html":"\u003ciframe width=\"400\" height=\"225\" src=\"https://www.youtube.com/embed/zkANQ9l7YDM?feature=oembed\u0026autoplay=1\u0026iv_load_policy=3\" frameborder=\"0\" allow=\"accelerometer; autoplay; clipboard-write; encrypted-media; gyroscope; picture-in-picture\" allowfullscreen\u003e\u003c/iframe\u003e","video_html_width":400,"video_html_height":225,"from_url":"https://www.youtube.com/watch?v=zkANQ9l7YDM\u0026amp;index=10","original_url":"https://www.youtube.com/watch?v=zkANQ9l7YDM\u0026amp;list=PLx8bw5NQypskGEy8ARntIDxKmXcBEoRZQ\u0026amp;index=10"}],"team":"T03C4RC8V","replace_original":false,"delete_original":false,"blocks":[{"type":"rich_text","block_id":"kePo"}]},{"client_msg_id":"34706c32-7057-45e0-9fa4-c4cff501131b","type":"message","user":"U03C4RC8X","text":"開発環境でだけど…","ts":"1613750644.109200","team":"T03C4RC8V","reactions":[{"name":"sugoi","count":4,"users":["U01ATUT6PL3","UFP0GQZ4K","U9S4G0LJW","U01BY3SDBRS"]}],"replace_original":false,"delete_original":false,"blocks":[{"type":"rich_text","block_id":"VnfzF"}]},{"client_msg_id":"924ed7b9-5652-41ea-98a8-0874cea0c8ab","type":"message","user":"U03C4RC8X","text":"スタディサプリ毎日使ってます","ts":"1613750628.108800","team":"T03C4RC8V","replace_original":false,"delete_original":false,"blocks":[{"type":"rich_text","block_id":"=/x"}]}]
