[{"type":"message","user":"U0132E68E0Z","text":"<@U0132E68E0Z> has joined the channel","ts":"1588101626.321300","subtype":"channel_join","replace_original":false,"delete_original":false,"blocks":null},{"client_msg_id":"47d31fe0-1228-4020-bc37-e0a050e266f5","type":"message","user":"U7B4ZD49X","text":"これ前からあったやつですね。。。\nプラグインを乗り換えたときに前のプラグインはやってくれていたことを新しいプラグインはやってくれてないことで再発したみたいです。。。\nお騒がせしました。","ts":"1588120450.321800","thread_ts":"1588080745.320400","parent_user_id":"U7B4ZD49X","team":"T03C4RC8V","replace_original":false,"delete_original":false,"blocks":[{"type":"rich_text","block_id":"KxYq"}],"source_team":"T03C4RC8V","user_team":"T03C4RC8V"},{"client_msg_id":"f75ff27d-ffe6-41d9-b4e5-47c0dfe3d52b","type":"message","user":"UBRTB4N5C","text":"X11 のクリップボード(セレクション)ってコピーした側のプロセスがずっと内容を持ってないといけないんじゃなかったっけ…。\n履歴を取る何かを入れてたらそこが代わりに持っておいてくれる可能性はありそうだけど。","ts":"1588127175.323100","team":"T03C4RC8V","replace_original":false,"delete_original":false,"blocks":[{"type":"rich_text","block_id":"Kk18i"}],"source_team":"T03C4RC8V","user_team":"T03C4RC8V"},{"client_msg_id":"A084569F-59CA-4CD1-93E9-903CC3345D84","type":"message","user":"UDDCM376D","text":"あんまりx11のこと分かってないんすけど、\nx11ってプロセスで動いてるんですよね？","ts":"1588138751.324600","team":"T03C4RC8V","replace_original":false,"delete_original":false,"blocks":[{"type":"rich_text","block_id":"4/t"}],"source_team":"T03C4RC8V","user_team":"T03C4RC8V"},{"client_msg_id":"ff5629d7-05e7-4215-88d6-d4abe037519e","type":"message","user":"U0M7GCBPD","text":"プロセスですよ","ts":"1588139736.325100","team":"T03C4RC8V","replace_original":false,"delete_original":false,"blocks":[{"type":"rich_text","block_id":"yDhx"}],"source_team":"T03C4RC8V","user_team":"T03C4RC8V"},{"client_msg_id":"776519a5-1e94-4528-acb9-b4ee96eb4669","type":"message","user":"U0M7GCBPD","text":"&gt; X11 のクリップボード(セレクション)ってコピーした側のプロセスがずっと内容を持ってないといけないんじゃなかったっけ…。\nそうだったはず","ts":"1588139744.325400","team":"T03C4RC8V","replace_original":false,"delete_original":false,"blocks":[{"type":"rich_text","block_id":"eo3b"}],"source_team":"T03C4RC8V","user_team":"T03C4RC8V"},{"client_msg_id":"8e02ce70-00da-43a0-8a56-65e81efd1d30","type":"message","user":"U0M7GCBPD","text":"アプリ A でなにかコピーして、アプリ B にペーストしようとした場合、アプリ A がすでに終了してたらペーストできなかったはず","ts":"1588139850.326200","team":"T03C4RC8V","replace_original":false,"delete_original":false,"blocks":[{"type":"rich_text","block_id":"LT5U"}],"source_team":"T03C4RC8V","user_team":"T03C4RC8V"},{"client_msg_id":"83922fd5-acf8-41e8-b2de-50b29a0735fd","type":"message","user":"U0M7GCBPD","text":"その都度通信とかしてるんじゃなかったっけ（たしか）","ts":"1588139933.326800","edited":{"user":"U0M7GCBPD","ts":"1588139962.000000"},"team":"T03C4RC8V","replace_original":false,"delete_original":false,"blocks":[{"type":"rich_text","block_id":"+eR"}],"source_team":"T03C4RC8V","user_team":"T03C4RC8V"},{"client_msg_id":"ca4d1224-53d2-4097-86de-be1baafd506d","type":"message","user":"UDDCM376D","text":"なるほど","ts":"1588149135.327200","team":"T03C4RC8V","replace_original":false,"delete_original":false,"blocks":[{"type":"rich_text","block_id":"UgJt"}],"source_team":"T03C4RC8V","user_team":"T03C4RC8V"},{"client_msg_id":"0bdfb2a3-a44e-40e8-91ec-a8492b5a419d","type":"message","user":"UDDCM376D","text":"Vimの場合はレジスタをviminfoに保持しているから問題ないけど、他のアプリは都度プロセスか","ts":"1588149173.328100","team":"T03C4RC8V","replace_original":false,"delete_original":false,"blocks":[{"type":"rich_text","block_id":"S7fOi"}],"source_team":"T03C4RC8V","user_team":"T03C4RC8V"},{"client_msg_id":"9c9e7b32-7a33-46b2-9839-e75864dab823","type":"message","user":"UEB17JJJE","text":"これわかりやすいですね\n<https://www.uninformativ.de/blog/postings/2017-04-02/0/POSTING-en.html|https://www.uninformativ.de/blog/postings/2017-04-02/0/POSTING-en.html>","ts":"1588152804.328800","team":"T03C4RC8V","reactions":[{"name":"eyes","count":1,"users":["U7B4ZD49X"]}],"replace_original":false,"delete_original":false,"blocks":[{"type":"rich_text","block_id":"sSB6"}],"source_team":"T03C4RC8V","user_team":"T03C4RC8V"},{"client_msg_id":"968e9ee3-6dfb-4ad1-990d-619adae25bbb","type":"message","user":"U03C6TEAZ","text":"x11 のはクリップボードでなくセレクションという x11 atom を使ったプロセス間通信なのでプロセスが死ぬとセレクションも消えます。","ts":"1588152953.330400","team":"T03C4RC8V","reactions":[{"name":"sasumatsu","count":2,"users":["U0M7GCBPD","U7B4ZD49X"]}],"replace_original":false,"delete_original":false,"blocks":[{"type":"rich_text","block_id":"RmPGf"}],"source_team":"T03C4RC8V","user_team":"T03C4RC8V"},{"client_msg_id":"fcf5252b-70d9-43ee-b3b8-64b62e2dedc1","type":"message","user":"U03C6TEAZ","text":"クリップボード的に使うにはクリップボードマネージャを動かす必要があります。","ts":"1588152994.331400","team":"T03C4RC8V","replace_original":false,"delete_original":false,"blocks":[{"type":"rich_text","block_id":"fr=4"}],"source_team":"T03C4RC8V","user_team":"T03C4RC8V"}]
